Metadata-Version: 2.2
Name: WinColl
Version: 1.2
Summary: Simple rocks-and-diamonds game
Author-email: Reuben Thomas <rrt@sc3d.org>
License: GPL v3 or later
Project-URL: Homepage, https://github.com/rrthomas/wincoll
Classifier: Environment :: X11 Applications
Classifier: Environment :: MacOS X
Classifier: Environment :: Win32 (MS Windows)
Classifier: Topic :: Games/Entertainment :: Puzzle Games
Classifier: Programming Language :: Python :: 3
Requires-Python: >=3.12
License-File: COPYING
Requires-Dist: chambercourt>=0.9.26
